hikaru/model/rel_1_27/__init__.py
hikaru/model/rel_1_27/deprecations.py
hikaru/model/rel_1_27/unversioned.py
hikaru/model/rel_1_27/versions.py
hikaru/model/rel_1_27/v1/__init__.py
hikaru/model/rel_1_27/v1/documents.py
hikaru/model/rel_1_27/v1/v1.py
hikaru/model/rel_1_27/v1/watchables.py
hikaru/model/rel_1_27/v1alpha1/__init__.py
hikaru/model/rel_1_27/v1alpha1/documents.py
hikaru/model/rel_1_27/v1alpha1/v1alpha1.py
hikaru/model/rel_1_27/v1alpha1/watchables.py
hikaru/model/rel_1_27/v1alpha2/__init__.py
hikaru/model/rel_1_27/v1alpha2/documents.py
hikaru/model/rel_1_27/v1alpha2/v1alpha2.py
hikaru/model/rel_1_27/v1alpha2/watchables.py
hikaru/model/rel_1_27/v1beta1/__init__.py
hikaru/model/rel_1_27/v1beta1/documents.py
hikaru/model/rel_1_27/v1beta1/v1beta1.py
hikaru/model/rel_1_27/v1beta2/__init__.py
hikaru/model/rel_1_27/v1beta2/documents.py
hikaru/model/rel_1_27/v1beta2/v1beta2.py
hikaru/model/rel_1_27/v1beta2/watchables.py
hikaru/model/rel_1_27/v1beta3/__init__.py
hikaru/model/rel_1_27/v1beta3/documents.py
hikaru/model/rel_1_27/v1beta3/v1beta3.py
hikaru/model/rel_1_27/v1beta3/watchables.py
hikaru/model/rel_1_27/v2/__init__.py
hikaru/model/rel_1_27/v2/documents.py
hikaru/model/rel_1_27/v2/v2.py
hikaru/model/rel_1_27/v2/watchables.py
hikaru_model_27-1.1.1.dist-info/LICENSE
hikaru_model_27-1.1.1.dist-info/METADATA
hikaru_model_27-1.1.1.dist-info/WHEEL
hikaru_model_27-1.1.1.dist-info/top_level.txt
hikaru_model_27-1.1.1.dist-info/RECORD
